examples/__init__.py
examples/examples.py
examples/flask_examples.py
examples/generate_jwt_keys.py
python_errors/__init__.py
python_errors/config.py
python_errors/handle_traceback.py
python_errors/secure.py
python_errors/secure_flask.py
python_errors-0.0.9.dist-info/LICENSE
python_errors-0.0.9.dist-info/METADATA
python_errors-0.0.9.dist-info/WHEEL
python_errors-0.0.9.dist-info/top_level.txt
python_errors-0.0.9.dist-info/RECORD
