Metadata-Version: 2.2
Name: python-errors
Version: 0.0.9
Summary: A library for reducing and identifying critical errors in Python code.
Home-page: https://github.com/RoyalGr4pe/python-errors
Author: Nick
Author-email: njames.programming@example.com
Classifier: Programming Language :: Python :: 3
Classifier: License :: OSI Approved :: MIT License
Classifier: Operating System :: OS Independent
Requires-Python: >=3.6
License-File: LICENSE
Dynamic: author
Dynamic: author-email
Dynamic: classifier
Dynamic: description
Dynamic: description-content-type
Dynamic: home-page
Dynamic: requires-python
Dynamic: summary
